<annotation>
	<folder>samples</folder>
	<filename>b43nw.png</filename>
	<path>C:\Users\augus\Documents\percepção computacional\labelimg\samples\b43nw.png</path>
	<source>
		<database>Unknown</database>
	</source>
	<size>
		<width>200</width>
		<height>50</height>
		<depth>1</depth>
	</size>
	<segmented>0</segmented>
	<object>
		<name>b</name>
		<pose>Unspecified</pose>
		<truncated>0</truncated>
		<difficult>0</difficult>
		<bndbox>
			<xmin>29</xmin>
			<ymin>10</ymin>
			<xmax>50</xmax>
			<ymax>44</ymax>
		</bndbox>
	</object>
	<object>
		<name>4</name>
		<pose>Unspecified</pose>
		<truncated>0</truncated>
		<difficult>0</difficult>
		<bndbox>
			<xmin>51</xmin>
			<ymin>11</ymin>
			<xmax>72</xmax>
			<ymax>44</ymax>
		</bndbox>
	</object>
	<object>
		<name>3</name>
		<pose>Unspecified</pose>
		<truncated>0</truncated>
		<difficult>0</difficult>
		<bndbox>
			<xmin>74</xmin>
			<ymin>11</ymin>
			<xmax>92</xmax>
			<ymax>46</ymax>
		</bndbox>
	</object>
	<object>
		<name>n</name>
		<pose>Unspecified</pose>
		<truncated>0</truncated>
		<difficult>0</difficult>
		<bndbox>
			<xmin>93</xmin>
			<ymin>18</ymin>
			<xmax>112</xmax>
			<ymax>45</ymax>
		</bndbox>
	</object>
	<object>
		<name>w</name>
		<pose>Unspecified</pose>
		<truncated>0</truncated>
		<difficult>0</difficult>
		<bndbox>
			<xmin>111</xmin>
			<ymin>18</ymin>
			<xmax>135</xmax>
			<ymax>46</ymax>
		</bndbox>
	</object>
</annotation>
